<pnp:Provisioning xmlns:pnp="http://schemas.dev.office.com/PnP/2019/09/ProvisioningSchema"
                  Author="John White"
                  Generator="Human being"
                  Version="1.0"
                  Description="Hub Site"
                  DisplayName="Global Marketing"
                  ImagePreviewUrl="https://raw.githubusercontent.com/SharePoint/sp-dev-provisioning-templates/master/site/theperspective/top-global-marketing.png">

  <pnp:Preferences Author="John Black" Version="1.0" Generator="Human being :-)">
    <pnp:Parameters>
      <pnp:Parameter Key="SiteTitle">Communications</pnp:Parameter>
      <pnp:Parameter Key="SiteUrl">/sites/Communications</pnp:Parameter>
    </pnp:Parameters>
  </pnp:Preferences>
  <pnp:Sequence ID="sequence">
    <pnp:SiteCollections>
      <pnp:SiteCollection xmlns:xsi="http://www.w3.org/2001/XMLSchema-instance" xsi:type="pnp:TeamSiteNoGroup" ProvisioningId="COMMUNICATIONS" Title="{parameter:SiteTitle}" Description="" Url="{hosturl}{parameter:SiteUrl}" Owner="{CurrentUserLoginName}">
        <pnp:Templates>
          <pnp:ProvisioningTemplateReference ID="COMMUNICATIONS-TEMPLATE"/>
        </pnp:Templates>
      </pnp:SiteCollection>
    </pnp:SiteCollections>
  </pnp:Sequence>
  <pnp:Templates ID="SITE-TEMPLATES">
    <pnp:ProvisioningTemplate ID="COMMUNICATIONS-TEMPLATE" Version="1" BaseSiteTemplate="STS#3" Scope="RootSite">
      <pnp:Theme Name="">
        {
        "neutralPrimaryAlt":  "#8d8b8a",
        "themeLighterAlt":  "#faf4f9",
        "black":  "#494847",
        "themeTertiary":  "#b473a5",
        "primaryBackground":  "#ffffff",
        "neutralQuaternaryAlt":  "#dadada",
        "accent":  "#17717A",
        "themePrimary":  "#833471",
        "neutralSecondary":  "#a3a2a0",
        "themeLighter":  "#ebd4e6",
        "themeDark":  "#632855",
        "neutralPrimary":  "#323130",
        "neutralLighterAlt":  "#f8f8f8",
        "neutralLighter":  "#f4f4f4",
        "neutralDark":  "#605e5d",
        "neutralQuaternary":  "#d0d0d0",
        "neutralLight":  "#eaeaea",
        "primaryText":  "#333333",
        "themeDarker":  "#491d3f",
        "neutralTertiaryAlt":  "#c8c8c8",
        "themeDarkAlt":  "#752f65",
        "white":  "#ffffff",
        "bodyBackground":  "#ffffff",
        "themeSecondary":  "#91447f",
        "bodyText":  "#333333",
        "disabledBackground":  "# f4f4f4",
        "neutralTertiary":  "#bab8b7",
        "themeLight":  "#dab2d0",
        "disabledText":  "#c8c8c8"
        }
      </pnp:Theme>
      <pnp:WebSettings NoCrawl="false" WelcomePage="SitePages/Home.aspx" SiteLogo="{hosturl}{site}/SiteAssets/communications_logo.jpg" CommentsOnSitePagesDisabled="false" QuickLaunchEnabled="false" SearchScope="DefaultScope" />
      <pnp:Navigation AddNewPagesToNavigation="true" CreateFriendlyUrlsForNewPages="true">
        <pnp:GlobalNavigation NavigationType="Structural">
          <pnp:StructuralNavigation RemoveExistingNodes="true" />
        </pnp:GlobalNavigation>
        <pnp:CurrentNavigation NavigationType="StructuralLocal">
          <pnp:StructuralNavigation RemoveExistingNodes="true">
            <pnp:NavigationNode Title="Home" Url="{site}" />
            <pnp:NavigationNode Title="Notebook" Url="{site}" IsExternal="true" />
            <pnp:NavigationNode Title="Team Calendar" Url="https://outlook.office365.com" IsExternal="true" />
            <pnp:NavigationNode Title="Team Documents" Url="{site}/Shared Documents/Forms/AllItems.aspx" />
            <pnp:NavigationNode Title="Shared with us" Url="{site}" />
            <pnp:NavigationNode Title="Teams Channel" Url="{site}" />
            <pnp:NavigationNode Title="Comms OneNote" Url="{site}" IsExternal="true" />
            <pnp:NavigationNode Title="Strategy Reviews" Url="{site}" />
            <pnp:NavigationNode Title="Press Releases" Url="{site}" />
            <pnp:NavigationNode Title="Legal" Url="{site}" />
          </pnp:StructuralNavigation>
        </pnp:CurrentNavigation>
      </pnp:Navigation>
      <pnp:Files>
        <pnp:File Src="SiteAssets/communications_logo.jpg" Folder="SiteAssets" Overwrite="true" Level="Published"/>
        <pnp:File Src="SiteAssets/SitePages/Communications/flysafe-thumb.jpg" Folder="SiteAssets/SitePages/Communications" Overwrite="true" Level="Published" />
        <pnp:File Src="SiteAssets/SitePages/Communications/farm-salmon-fishing-aerial-fpv-drone-photography-PFVEAUC.jpg" Folder="SiteAssets/SitePages/Communications" Overwrite="true" Level="Published" />
        <pnp:File Src="SiteAssets/SitePages/Singapore-trip-report/39311-Singapore1920.1080.jpg" Folder="SiteAssets/SitePages/Singapore-trip-report" Overwrite="true" Level="Published" />
        <pnp:File Src="SiteAssets/SitePages/Singapore-trip-report/2200814861-Singapore1920.1080.jpg" Folder="SiteAssets/SitePages/Singapore-trip-report" Overwrite="true" Level="Published" />
        <pnp:File Src="SiteAssets/SitePages/Singapore-trip-report/9418337674singapore-airport.jpg" Folder="SiteAssets/SitePages/Singapore-trip-report" Overwrite="true" Level="Published" />
        <pnp:File Src="SiteAssets/SitePages/Singapore-trip-report/7851051212sergio-sala-1433115-unsplash.jpg" Folder="SiteAssets/SitePages/Singapore-trip-report" Overwrite="true" Level="Published" />
        <pnp:File Src="SiteAssets/SitePages/Singapore-trip-report/5404572832victor-garcia-741316-unsplash.jpg" Folder="SiteAssets/SitePages/Singapore-trip-report" Overwrite="true" Level="Published" />
        <pnp:File Src="SiteAssets/SitePages/Singapore-trip-report/2938599925hu-chen-656089-unsplash.jpg" Folder="SiteAssets/SitePages/Singapore-trip-report" Overwrite="true" Level="Published" />
        <pnp:File Src="SiteAssets/SitePages/Singapore-trip-report/5735711170-henry-co-180108-unsplash.jpg" Folder="SiteAssets/SitePages/Singapore-trip-report" Overwrite="true" Level="Published" />
        <pnp:File Src="SiteAssets/SitePages/Singapore-trip-report/80811432091200px-Singapore_skyline_at_sunset_viewed_from_Gardens_by_the_Bay_East_-_20120426.jpg" Folder="SiteAssets/SitePages/Singapore-trip-report" Overwrite="true" Level="Published" />
        <pnp:File Src="SiteAssets/SitePages/Singapore-trip-report/6881280523building-construction.jpg" Folder="SiteAssets/SitePages/Singapore-trip-report" Overwrite="true" Level="Published" />
        <pnp:File Src="SiteAssets/SitePages/Singapore-trip-report/5735711170-henry-co-180108-unsplash.jpg" Folder="SiteAssets/SitePages/Singapore-trip-report" Overwrite="true" Level="Published" />
        <pnp:File Src="SiteAssets/SitePages/How-apps-can-make-corporate-communications-easier/rawpixel-597438-unsplash.jpg" Folder="SiteAssets/SitePages/How-apps-can-make-corporate-communications-easier" Overwrite="true" Level="Published" />
        <pnp:File Src="SiteAssets/SitePages/Welcome-to--CommsChat/studio-microphone-in-front-of-radio-station-PBWVM4G.jpg" Folder="SiteAssets/SitePages/Welcome-to--CommsChat" Overwrite="true" Level="Published" />
        <pnp:File Src="SiteAssets/SitePages/Strategic-communication--How-to-develop-strategic-massaging-and-positioning/business-people-planning-strategy-in-office-GRVBWNJ.jpg" Folder="SiteAssets/SitePages/Strategic-communication--How-to-develop-strategic-massaging-and-positioning" Overwrite="true" Level="Published" />
        <pnp:File Src="Shared Documents/Campaign Sales Data.xlsx" Folder="Shared Documents" Overwrite="true" Level="Published" />
        <pnp:File Src="Shared Documents/Comms_Q1_ResearchDev-mobile.pptx" Folder="Shared Documents" Overwrite="true" Level="Published" />
        <pnp:File Src="Shared Documents/Contoso Electroncs Announces Electronic Events Legal Department Moves.docx" Folder="Shared Documents" Overwrite="true" Level="Published" />
        <pnp:File Src="Shared Documents/Contoso Electronics Announces Electronic Events Legal Department Moves.pdf" Folder="Shared Documents" Overwrite="true" Level="Published" />
        <pnp:File Src="Shared Documents/Contoso Electronics Projects Next Years Earnings.docx" Folder="Shared Documents" Overwrite="true" Level="Published" />
        <pnp:File Src="Shared Documents/Contoso Electronics Projects Next Years Earnings.pdf" Folder="Shared Documents" Overwrite="true" Level="Published" />
        <pnp:File Src="Shared Documents/Contoso Marketing Principles.pptx" Folder="Shared Documents" Overwrite="true" Level="Published" />
        <pnp:File Src="Shared Documents/Contoso Purchasing Data - Q1 KJ copy.xlsx" Folder="Shared Documents" Overwrite="true" Level="Published" />
        <pnp:File Src="Shared Documents/Customer Feedback.pptx" Folder="Shared Documents" Overwrite="true" Level="Published" />
        <pnp:File Src="Shared Documents/Divisional Sales Report.docx" Folder="Shared Documents" Overwrite="true" Level="Published" />
        <pnp:File Src="Shared Documents/European Tech Trends.docx" Folder="Shared Documents" Overwrite="true" Level="Published" />
        <pnp:File Src="Shared Documents/Fabrikam3DPrinterBrochure.pptx" Folder="Shared Documents" Overwrite="true" Level="Published" />
        <pnp:File Src="Shared Documents/New York Launch Event - Packaging Poll.xlsb" Folder="Shared Documents" Overwrite="true" Level="Published" />
        <pnp:File Src="Shared Documents/Singapore_CustomerBriefings.pptx" Folder="Shared Documents" Overwrite="true" Level="Published" />
        <pnp:File Src="Shared Documents/Singapore_CustomerBriefings_97616.pptx" Folder="Shared Documents" Overwrite="true" Level="Published" />
        <pnp:File Src="Shared Documents/strategic-messaging-map.pdf" Folder="Shared Documents" Overwrite="true" Level="Published" />
        <pnp:File Src="Shared Documents/Web_hero_landing.png" Folder="Shared Documents" Overwrite="true" Level="Published" />
        <pnp:File Src="Shared Documents/Trip Reports/Singapore_CustomerBriefings.pptx" Folder="Shared Documents/Trip Reports" Overwrite="true" Level="Published" />
      </pnp:Files>
      <pnp:Lists>
        <pnp:ListInstance Title="Documents" DocumentTemplate="{site}/Shared Documents/Forms/template.dotx" OnQuickLaunch="true" TemplateType="101" Url="Shared Documents" EnableVersioning="true" MinorVersionLimit="0" MaxVersionLimit="500" DraftVersionVisibility="0" TemplateFeatureID="00bfea71-e717-4e80-aa17-d0c71b360101" ContentTypesEnabled="true" EnableAttachments="false" ListExperience="NewExperience" DefaultDisplayFormUrl="{site}/Shared Documents/Forms/DispForm.aspx" DefaultEditFormUrl="{site}/Shared Documents/Forms/EditForm.aspx" DefaultNewFormUrl="{site}/Shared Documents/Forms/Upload.aspx" ImageUrl="/_layouts/15/images/itdl.png?rev=44" IrmExpire="false" IrmReject="false" IsApplicationList="false" ValidationFormula="" ValidationMessage="">
          <pnp:ContentTypeBindings>
            <pnp:ContentTypeBinding ContentTypeID="0x0101" Default="true" />
            <pnp:ContentTypeBinding ContentTypeID="0x0120" />
          </pnp:ContentTypeBindings>
          <pnp:Views>
            <View Name="AllDocuments" DefaultView="TRUE" MobileView="TRUE" MobileDefaultView="TRUE" Type="HTML" DisplayName="All Documents" Url="{site}/Shared Documents/Forms/AllItems.aspx" Level="1" BaseViewID="1" ContentTypeID="0x" ImageUrl="/_layouts/15/images/dlicon.png?rev=47">
              <Query>
                <OrderBy>
                  <FieldRef Name="FileLeafRef" />
                </OrderBy>
              </Query>
              <ViewFields>
                <FieldRef Name="DocIcon" />
                <FieldRef Name="LinkFilename" />
                <FieldRef Name="Modified" />
                <FieldRef Name="Editor" />
              </ViewFields>
              <RowLimit Paged="TRUE">30</RowLimit>
              <JSLink>clienttemplates.js</JSLink>
            </View>
          </pnp:Views>
          <pnp:Folders>
            <pnp:Folder Name="Events"/>
            <pnp:Folder Name="General" />
            <pnp:Folder Name="Legal" />
            <pnp:Folder Name="Media" />
            <pnp:Folder Name="News from the team" />
            <pnp:Folder Name="Press Release" />
          </pnp:Folders>
        </pnp:ListInstance>
      </pnp:Lists>
      <pnp:ClientSidePages>
        <pnp:ClientSidePage PageName="Home.aspx" PromoteAsNewsArticle="false" PromoteAsTemplate="false" Overwrite="true" Layout="Home" EnableComments="false" Title="Home" ThumbnailUrl="">
          <pnp:Header Type="Default" LayoutType="FullWidthImage" TextAlignment="Center" ShowTopicHeader="false" ShowPublishDate="false" TopicHeader="" AlternativeText="" Authors="" AuthorByLine="" AuthorByLineId="-1" />
          <pnp:Sections>
            <pnp:Section Order="1" Type="OneColumn">
              <pnp:Controls>
                <pnp:CanvasControl WebPartType="News" JsonControlData="{&quot;id&quot;: &quot;8c88f208-6c77-4bdb-86a0-0c47b4316588&quot;, &quot;instanceId&quot;: &quot;f7bfdec9-09c5-4fb6-bc97-3ba225d35ad4&quot;, &quot;title&quot;: &quot;News&quot;, &quot;description&quot;: &quot;&quot;, &quot;dataVersion&quot;: &quot;1.11&quot;, &quot;properties&quot;: {&quot;layoutId&quot;:&quot;GridNews&quot;,&quot;dataProviderId&quot;:&quot;news&quot;,&quot;emptyStateHelpItemsCount&quot;:&quot;1&quot;,&quot;showChrome&quot;:true,&quot;carouselSettings&quot;:{&quot;autoplay&quot;:false,&quot;autoplaySpeed&quot;:5,&quot;dots&quot;:true,&quot;lazyLoad&quot;:true},&quot;showNewsMetadata&quot;:{&quot;showSocialActions&quot;:true,&quot;showAuthor&quot;:true,&quot;showDate&quot;:true},&quot;prefetchCount&quot;:4,&quot;filters&quot;:[{&quot;filterType&quot;:1,&quot;value&quot;:&quot;&quot;,&quot;values&quot;:[]}],&quot;newsDataSourceProp&quot;:1,&quot;newsSiteList&quot;:[],&quot;renderItemsSliderValue&quot;:4,&quot;webId&quot;:&quot;{siteid}&quot;,&quot;siteId&quot;:&quot;{sitecollectionid}&quot;,&quot;pinnedItems&quot;:[null,null,null,null,null,null,null,null,null,null,null,null,null,null,null],&quot;serializedFilterQuery&quot;:&quot;&lt;Where&gt;&lt;Eq&gt;&lt;FieldRef Name=\&quot;FSObjType\&quot; /&gt;&lt;Value Type=\&quot;Integer\&quot;&gt;0&lt;/Value&gt;&lt;/Eq&gt;&lt;/Where&gt;&quot;,&quot;templateId&quot;:&quot;GridNews&quot;,&quot;propsLastEdited&quot;:&quot;2019-09-17T03:33:39.47Z&quot;,&quot;compactMode&quot;:false}, &quot;serverProcessedContent&quot;: {&quot;htmlStrings&quot;:{},&quot;searchablePlainTexts&quot;:{&quot;title&quot;:&quot;Communication news&quot;},&quot;imageSources&quot;:{},&quot;links&quot;:{&quot;baseUrl&quot;:&quot;{site}&quot;}}, &quot;dynamicDataPaths&quot;: {}, &quot;dynamicDataValues&quot;: {}}" ControlId="8c88f208-6c77-4bdb-86a0-0c47b4316588" Order="1" Column="1" />
              </pnp:Controls>
            </pnp:Section>
            <pnp:Section Order="2" Type="TwoColumnVerticalSection" VerticalSectionEmphasis="Soft">
              <pnp:Controls>
                <pnp:CanvasControl WebPartType="List" JsonControlData="{&quot;id&quot;: &quot;f92bf067-bc19-489e-a556-7fe95f508720&quot;, &quot;instanceId&quot;: &quot;6daef298-9b66-474f-addc-716900c762f2&quot;, &quot;title&quot;: &quot;Document library&quot;, &quot;description&quot;: &quot;Add a document library&quot;, &quot;dataVersion&quot;: &quot;1.0&quot;, &quot;properties&quot;: {&quot;isDocumentLibrary&quot;:true,&quot;selectedListId&quot;:&quot;{listid:Documents}&quot;,&quot;selectedListUrl&quot;:&quot;{site}/Shared Documents&quot;,&quot;webRelativeListUrl&quot;:&quot;/Shared Documents&quot;,&quot;selectedViewId&quot;:&quot;{viewid:Documents,All Documents}&quot;}, &quot;serverProcessedContent&quot;: {&quot;htmlStrings&quot;:{},&quot;searchablePlainTexts&quot;:{&quot;listTitle&quot;:&quot;Documents&quot;},&quot;imageSources&quot;:{},&quot;links&quot;:{}}, &quot;dynamicDataPaths&quot;: {}, &quot;dynamicDataValues&quot;: {&quot;filterBy&quot;:{}}}" ControlId="f92bf067-bc19-489e-a556-7fe95f508720" Order="1" Column="1" />
                <pnp:CanvasControl WebPartType="SiteActivity" JsonControlData="{&quot;id&quot;: &quot;eb95c819-ab8f-4689-bd03-0c2d65d47b1f&quot;, &quot;instanceId&quot;: &quot;f2a8650b-5ea0-4ac2-9cde-56e0fd0279b0&quot;, &quot;title&quot;: &quot;Site activity&quot;, &quot;description&quot;: &quot;&quot;, &quot;dataVersion&quot;: &quot;1.0&quot;, &quot;properties&quot;: {&quot;maxItems&quot;:&quot;4&quot;}, &quot;serverProcessedContent&quot;: {&quot;htmlStrings&quot;:{},&quot;searchablePlainTexts&quot;:{},&quot;imageSources&quot;:{},&quot;links&quot;:{}}, &quot;dynamicDataPaths&quot;: {}, &quot;dynamicDataValues&quot;: {}}" ControlId="eb95c819-ab8f-4689-bd03-0c2d65d47b1f" Order="1" Column="2" />
                <pnp:CanvasControl WebPartType="QuickLinks" JsonControlData="{&quot;id&quot;: &quot;c70391ea-0b10-4ee9-b2b4-006d3fcad0cd&quot;, &quot;instanceId&quot;: &quot;97354def-80c6-45d1-969d-80d4f77bf6b2&quot;, &quot;title&quot;: &quot;Quick links&quot;, &quot;description&quot;: &quot;Add links to important documents and pages.&quot;, &quot;dataVersion&quot;: &quot;2.2&quot;, &quot;properties&quot;: {&quot;items&quot;:[{&quot;sourceItem&quot;:{&quot;guids&quot;:{&quot;siteId&quot;:&quot;{sitecollectionid}&quot;,&quot;webId&quot;:&quot;{siteid}&quot;,&quot;listId&quot;:&quot;{listid:Site Pages}&quot;,&quot;uniqueId&quot;:&quot;{pageuniqueid:SitePages/Home.aspx}&quot;},&quot;itemType&quot;:0,&quot;fileExtension&quot;:&quot;.ASPX&quot;,&quot;progId&quot;:null},&quot;thumbnailType&quot;:1,&quot;id&quot;:3,&quot;image&quot;:{&quot;guids&quot;:{&quot;listId&quot;:&quot;{listid:Site Assets}&quot;,&quot;uniqueId&quot;:&quot;{fileuniqueid:SiteAssets/SitePages/Communications/flysafe-thumb.jpg}&quot;,&quot;webId&quot;:&quot;{siteid}&quot;,&quot;siteId&quot;:&quot;{sitecollectionid}&quot;},&quot;imageFit&quot;:2}},{&quot;sourceItem&quot;:{&quot;guids&quot;:{&quot;siteId&quot;:&quot;{sitecollectionid}&quot;,&quot;webId&quot;:&quot;{siteid}&quot;,&quot;listId&quot;:&quot;{listid:Site Pages}&quot;,&quot;uniqueId&quot;:&quot;{pageuniqueid:SitePages/Home.aspx}&quot;},&quot;itemType&quot;:0,&quot;fileExtension&quot;:&quot;.ASPX&quot;,&quot;progId&quot;:null},&quot;thumbnailType&quot;:1,&quot;id&quot;:2,&quot;image&quot;:{&quot;guids&quot;:{&quot;listId&quot;:&quot;{listid:Site Assets}&quot;,&quot;uniqueId&quot;:&quot;{fileuniqueid:SiteAssets/SitePages/Communications/farm-salmon-fishing-aerial-fpv-drone-photography-PFVEAUC.jpg}&quot;,&quot;webId&quot;:&quot;{siteid}&quot;,&quot;siteId&quot;:&quot;{sitecollectionid}&quot;},&quot;imageFit&quot;:2}},{&quot;sourceItem&quot;:{&quot;itemType&quot;:2,&quot;fileExtension&quot;:&quot;&quot;,&quot;progId&quot;:&quot;&quot;},&quot;thumbnailType&quot;:3,&quot;id&quot;:1}],&quot;isMigrated&quot;:true,&quot;layoutId&quot;:&quot;FilmStrip&quot;,&quot;shouldShowThumbnail&quot;:true,&quot;buttonLayoutOptions&quot;:{&quot;showDescription&quot;:false,&quot;buttonTreatment&quot;:2,&quot;iconPositionType&quot;:2,&quot;textAlignmentVertical&quot;:2,&quot;textAlignmentHorizontal&quot;:2,&quot;linesOfText&quot;:2},&quot;listLayoutOptions&quot;:{&quot;showDescription&quot;:false,&quot;showIcon&quot;:true},&quot;waffleLayoutOptions&quot;:{&quot;iconSize&quot;:1,&quot;onlyShowThumbnail&quot;:false},&quot;hideWebPartWhenEmpty&quot;:true,&quot;dataProviderId&quot;:&quot;QuickLinks&quot;,&quot;webId&quot;:&quot;{siteid}&quot;,&quot;siteId&quot;:&quot;{sitecollectionid}&quot;,&quot;pane_link_button&quot;:0}, &quot;serverProcessedContent&quot;: {&quot;htmlStrings&quot;:{},&quot;searchablePlainTexts&quot;:{&quot;title&quot;:&quot;Contoso in the news&quot;,&quot;items[0].title&quot;:&quot;FlySafe 2019 Propels Commercial Drone Industry Forward&quot;,&quot;items[1].title&quot;:&quot;Contoso Electronics enhances its geospatial data collection platform&quot;,&quot;items[2].title&quot;:&quot;Microsoft Ignite | Contoso Electronics&quot;,&quot;items[0].description&quot;:&quot;&quot;,&quot;items[1].description&quot;:&quot;&quot;,&quot;items[2].description&quot;:&quot;&quot;,&quot;items[0].altText&quot;:&quot;&quot;,&quot;items[1].altText&quot;:&quot;&quot;,&quot;items[2].altText&quot;:&quot;&quot;},&quot;imageSources&quot;:{&quot;items[0].image.url&quot;:&quot;{site}/SiteAssets/SitePages/Communications/flysafe-thumb.jpg&quot;,&quot;items[1].image.url&quot;:&quot;{site}/SiteAssets/SitePages/Communications/farm-salmon-fishing-aerial-fpv-drone-photography-PFVEAUC.jpg&quot;,&quot;items[2].rawPreviewImageUrl&quot;:&quot;https://img-prod-cms-rt-microsoft-com.akamaized.net/cms/api/am/imageFileData/RE3wtYV&quot;},&quot;links&quot;:{&quot;baseUrl&quot;:&quot;{site}&quot;,&quot;items[0].sourceItem.url&quot;:&quot;{site}/SitePages/Home.aspx&quot;,&quot;items[1].sourceItem.url&quot;:&quot;{site}/SitePages/Home.aspx&quot;,&quot;items[2].sourceItem.url&quot;:&quot;https://www.microsoft.com/en-us/ignite&quot;},&quot;componentDependencies&quot;:{&quot;layoutComponentId&quot;:&quot;8ac0c53c-e8d0-4e3e-87d0-7449eb0d4027&quot;}}, &quot;dynamicDataPaths&quot;: {}, &quot;dynamicDataValues&quot;: {}}" ControlId="c70391ea-0b10-4ee9-b2b4-006d3fcad0cd" Order="1" Column="3" />
                <pnp:CanvasControl WebPartType="QuickLinks" JsonControlData="{&quot;id&quot;: &quot;c70391ea-0b10-4ee9-b2b4-006d3fcad0cd&quot;, &quot;instanceId&quot;: &quot;48ec0a20-1b23-44d6-8cfb-4103baca158e&quot;, &quot;title&quot;: &quot;Quick links&quot;, &quot;description&quot;: &quot;Add links to important documents and pages.&quot;, &quot;dataVersion&quot;: &quot;2.2&quot;, &quot;properties&quot;: {&quot;items&quot;:[{&quot;sourceItem&quot;:{&quot;guids&quot;:{&quot;siteId&quot;:&quot;{sitecollectionid}&quot;,&quot;webId&quot;:&quot;{siteid}&quot;,&quot;listId&quot;:&quot;{listid:Site Pages}&quot;,&quot;uniqueId&quot;:&quot;{pageuniqueid:SitePages/Home.aspx}&quot;},&quot;itemType&quot;:0,&quot;fileExtension&quot;:&quot;.ASPX&quot;,&quot;progId&quot;:null},&quot;thumbnailType&quot;:3,&quot;id&quot;:6},{&quot;sourceItem&quot;:{&quot;guids&quot;:{&quot;siteId&quot;:&quot;{sitecollectionid}&quot;,&quot;webId&quot;:&quot;{siteid}&quot;,&quot;listId&quot;:&quot;{listid:Site Pages}&quot;,&quot;uniqueId&quot;:&quot;{pageuniqueid:SitePages/Home.aspx}&quot;},&quot;itemType&quot;:0,&quot;fileExtension&quot;:&quot;.ASPX&quot;,&quot;progId&quot;:null},&quot;thumbnailType&quot;:3,&quot;id&quot;:5},{&quot;sourceItem&quot;:{&quot;guids&quot;:{&quot;siteId&quot;:&quot;{sitecollectionid}&quot;,&quot;webId&quot;:&quot;{siteid}&quot;,&quot;listId&quot;:&quot;{listid:Site Pages}&quot;,&quot;uniqueId&quot;:&quot;{pageuniqueid:SitePages/Home.aspx}&quot;},&quot;itemType&quot;:0,&quot;fileExtension&quot;:&quot;.ASPX&quot;,&quot;progId&quot;:null},&quot;thumbnailType&quot;:3,&quot;id&quot;:4},{&quot;sourceItem&quot;:{&quot;guids&quot;:{&quot;siteId&quot;:&quot;{sitecollectionid}&quot;,&quot;webId&quot;:&quot;{siteid}&quot;,&quot;listId&quot;:&quot;{listid:Site Pages}&quot;,&quot;uniqueId&quot;:&quot;{pageuniqueid:SitePages/Home.aspx}&quot;},&quot;itemType&quot;:0,&quot;fileExtension&quot;:&quot;.ASPX&quot;,&quot;progId&quot;:null},&quot;thumbnailType&quot;:3,&quot;id&quot;:3},{&quot;sourceItem&quot;:{&quot;guids&quot;:{&quot;siteId&quot;:&quot;{sitecollectionid}&quot;,&quot;webId&quot;:&quot;{siteid}&quot;,&quot;listId&quot;:&quot;{listid:Site Pages}&quot;,&quot;uniqueId&quot;:&quot;{pageuniqueid:SitePages/Home.aspx}&quot;},&quot;itemType&quot;:0,&quot;fileExtension&quot;:&quot;.ASPX&quot;,&quot;progId&quot;:null},&quot;thumbnailType&quot;:3,&quot;id&quot;:2},{&quot;sourceItem&quot;:{&quot;guids&quot;:{&quot;siteId&quot;:&quot;{sitecollectionid}&quot;,&quot;webId&quot;:&quot;{siteid}&quot;,&quot;listId&quot;:&quot;{listid:Site Pages}&quot;,&quot;uniqueId&quot;:&quot;{pageuniqueid:SitePages/Home.aspx}&quot;},&quot;itemType&quot;:0,&quot;fileExtension&quot;:&quot;.ASPX&quot;,&quot;progId&quot;:null},&quot;thumbnailType&quot;:3,&quot;id&quot;:1}],&quot;isMigrated&quot;:true,&quot;layoutId&quot;:&quot;Button&quot;,&quot;shouldShowThumbnail&quot;:false,&quot;buttonLayoutOptions&quot;:{&quot;showDescription&quot;:false,&quot;buttonTreatment&quot;:3,&quot;iconPositionType&quot;:1,&quot;textAlignmentVertical&quot;:2,&quot;textAlignmentHorizontal&quot;:2,&quot;linesOfText&quot;:2},&quot;listLayoutOptions&quot;:{&quot;showDescription&quot;:false,&quot;showIcon&quot;:false},&quot;waffleLayoutOptions&quot;:{&quot;iconSize&quot;:1,&quot;onlyShowThumbnail&quot;:false},&quot;hideWebPartWhenEmpty&quot;:true,&quot;dataProviderId&quot;:&quot;QuickLinks&quot;,&quot;webId&quot;:&quot;{siteid}&quot;,&quot;siteId&quot;:&quot;{sitecollectionid}&quot;}, &quot;serverProcessedContent&quot;: {&quot;htmlStrings&quot;:{},&quot;searchablePlainTexts&quot;:{&quot;title&quot;:&quot;Resources&quot;,&quot;items[0].title&quot;:&quot;Content Calendar »&quot;,&quot;items[1].title&quot;:&quot;Legal &amp; Procurement »&quot;,&quot;items[2].title&quot;:&quot;Press release template »&quot;,&quot;items[3].title&quot;:&quot;Design requests »&quot;,&quot;items[4].title&quot;:&quot;Contoso brand guidelines »&quot;,&quot;items[5].title&quot;:&quot;Contoso media guidelines »&quot;,&quot;items[0].description&quot;:&quot;&quot;,&quot;items[1].description&quot;:&quot;&quot;,&quot;items[2].description&quot;:&quot;&quot;,&quot;items[3].description&quot;:&quot;&quot;,&quot;items[4].description&quot;:&quot;&quot;,&quot;items[5].description&quot;:&quot;&quot;,&quot;items[0].altText&quot;:&quot;&quot;,&quot;items[1].altText&quot;:&quot;&quot;,&quot;items[2].altText&quot;:&quot;&quot;,&quot;items[3].altText&quot;:&quot;&quot;,&quot;items[4].altText&quot;:&quot;&quot;,&quot;items[5].altText&quot;:&quot;&quot;},&quot;imageSources&quot;:{},&quot;links&quot;:{&quot;baseUrl&quot;:&quot;{site}&quot;,&quot;items[0].sourceItem.url&quot;:&quot;{site}/SitePages/Home.aspx&quot;,&quot;items[1].sourceItem.url&quot;:&quot;{site}/SitePages/Home.aspx&quot;,&quot;items[2].sourceItem.url&quot;:&quot;{site}/SitePages/Home.aspx&quot;,&quot;items[3].sourceItem.url&quot;:&quot;{site}/SitePages/Home.aspx&quot;,&quot;items[4].sourceItem.url&quot;:&quot;{site}/SitePages/Home.aspx&quot;,&quot;items[5].sourceItem.url&quot;:&quot;{site}/SitePages/Home.aspx&quot;},&quot;componentDependencies&quot;:{&quot;layoutComponentId&quot;:&quot;706e33c8-af37-4e7b-9d22-6e5694d92a6f&quot;}}, &quot;dynamicDataPaths&quot;: {}, &quot;dynamicDataValues&quot;: {}}" ControlId="c70391ea-0b10-4ee9-b2b4-006d3fcad0cd" Order="2" Column="3" />
                <pnp:CanvasControl WebPartType="Custom" JsonControlData="{&quot;id&quot;: &quot;81b57906-cbed-4bb1-9823-2e3314f46f28&quot;, &quot;instanceId&quot;: &quot;d6799af4-95c9-480c-b051-ee7373fe96ad&quot;, &quot;title&quot;: &quot;World clock&quot;, &quot;description&quot;: &quot;Show clocks for the time zones you choose&quot;, &quot;dataVersion&quot;: &quot;1.0&quot;, &quot;properties&quot;: {&quot;timeFormat&quot;:&quot;hm&quot;,&quot;dateFormat&quot;:&quot;mmm dd, yyyy&quot;,&quot;isSpecifyDateTimeFormats&quot;:true,&quot;shouldShowDayOfWeek&quot;:true,&quot;clockItems&quot;:[{&quot;location&quot;:&quot;Redmond, WA&quot;,&quot;useManualConfiguration&quot;:false,&quot;displayedLocation&quot;:&quot;Redmond, WA&quot;,&quot;isTimezoneResolved&quot;:true,&quot;windowsTimeZoneId&quot;:&quot;Pacific Standard Time&quot;,&quot;manualConfiguredTimezoneId&quot;:&quot;Pacific Standard Time&quot;},{&quot;location&quot;:&quot;Detroit, MI&quot;,&quot;useManualConfiguration&quot;:false,&quot;displayedLocation&quot;:&quot;Detroit, MI&quot;,&quot;isTimezoneResolved&quot;:true,&quot;windowsTimeZoneId&quot;:&quot;Eastern Standard Time&quot;,&quot;manualConfiguredTimezoneId&quot;:&quot;Eastern Standard Time&quot;},{&quot;location&quot;:&quot;London, London, United Kingdom&quot;,&quot;useManualConfiguration&quot;:false,&quot;displayedLocation&quot;:&quot;London, London, United Kingdom&quot;,&quot;isTimezoneResolved&quot;:true,&quot;windowsTimeZoneId&quot;:&quot;GMT Standard Time&quot;,&quot;manualConfiguredTimezoneId&quot;:&quot;GMT Standard Time&quot;},{&quot;location&quot;:&quot;New Delhi, India&quot;,&quot;useManualConfiguration&quot;:false,&quot;displayedLocation&quot;:&quot;New Delhi, India&quot;,&quot;isTimezoneResolved&quot;:true,&quot;windowsTimeZoneId&quot;:&quot;India Standard Time&quot;,&quot;manualConfiguredTimezoneId&quot;:&quot;India Standard Time&quot;},{&quot;location&quot;:&quot;Singapore, Singapore&quot;,&quot;useManualConfiguration&quot;:false,&quot;displayedLocation&quot;:&quot;Singapore, Singapore&quot;,&quot;isTimezoneResolved&quot;:true,&quot;windowsTimeZoneId&quot;:&quot;Singapore Standard Time&quot;,&quot;manualConfiguredTimezoneId&quot;:&quot;Singapore Standard Time&quot;}]}, &quot;serverProcessedContent&quot;: {&quot;htmlStrings&quot;:{},&quot;searchablePlainTexts&quot;:{&quot;webPartTitle&quot;:&quot;Team locations&quot;},&quot;imageSources&quot;:{},&quot;links&quot;:{}}, &quot;dynamicDataPaths&quot;: {}, &quot;dynamicDataValues&quot;: {}}" ControlId="81b57906-cbed-4bb1-9823-2e3314f46f28" Order="3" Column="3" />
                <pnp:CanvasControl WebPartType="People" JsonControlData="{&quot;id&quot;: &quot;7f718435-ee4d-431c-bdbf-9c4ff326f46e&quot;, &quot;instanceId&quot;: &quot;8eaf5558-d434-4257-aaf5-5cb4d9b101af&quot;, &quot;title&quot;: &quot;People&quot;, &quot;description&quot;: &quot;Display selected people and their profiles&quot;, &quot;dataVersion&quot;: &quot;1.3&quot;, &quot;properties&quot;: {&quot;layout&quot;:1,&quot;persons&quot;:[{&quot;id&quot;:&quot;MiriamG@contoso.com&quot;,&quot;role&quot;:&quot;Chief Marketing Officer&quot;},{&quot;id&quot;:&quot;DebraB@contoso.com&quot;,&quot;role&quot;:&quot;Administrative Assistant&quot;},{&quot;id&quot;:&quot;JoniS@contoso.com&quot;,&quot;role&quot;:&quot;Paralegal&quot;},{&quot;id&quot;:&quot;PradeepG@contoso.com&quot;,&quot;role&quot;:&quot;Accountant&quot;},{&quot;id&quot;:&quot;LeeG@contoso.com&quot;,&quot;role&quot;:&quot;Director&quot;},{&quot;id&quot;:&quot;GradyA@contoso.com&quot;,&quot;role&quot;:&quot;Designer&quot;},{&quot;id&quot;:&quot;AdeleV@contoso.com&quot;,&quot;role&quot;:&quot;Retail Manager&quot;}]}, &quot;serverProcessedContent&quot;: {&quot;htmlStrings&quot;:{},&quot;searchablePlainTexts&quot;:{&quot;title&quot;:&quot;Comms team contacts&quot;,&quot;persons[0].name&quot;:&quot;Miriam Graham&quot;,&quot;persons[1].name&quot;:&quot;Debra Berger&quot;,&quot;persons[2].name&quot;:&quot;Joni Sherman&quot;,&quot;persons[3].name&quot;:&quot;Pradeep Gupta&quot;,&quot;persons[4].name&quot;:&quot;Lee Gu&quot;,&quot;persons[5].name&quot;:&quot;Grady Archie&quot;,&quot;persons[6].name&quot;:&quot;Adele Vance&quot;,&quot;persons[0].email&quot;:&quot;MiriamG@contoso.com&quot;,&quot;persons[1].email&quot;:&quot;DebraB@contoso.com&quot;,&quot;persons[2].email&quot;:&quot;JoniS@contoso.com&quot;,&quot;persons[3].email&quot;:&quot;PradeepG@contoso.com&quot;,&quot;persons[4].email&quot;:&quot;LeeG@contoso.com&quot;,&quot;persons[5].email&quot;:&quot;GradyA@contoso.com&quot;,&quot;persons[6].email&quot;:&quot;AdeleV@contoso.com&quot;},&quot;imageSources&quot;:{},&quot;links&quot;:{}}, &quot;dynamicDataPaths&quot;: {}, &quot;dynamicDataValues&quot;: {}}" ControlId="7f718435-ee4d-431c-bdbf-9c4ff326f46e" Order="4" Column="3" />
              </pnp:Controls>
            </pnp:Section>
            <pnp:Section Order="3" Type="TwoColumnLeft">
              <pnp:Controls>
                <pnp:CanvasControl WebPartType="Custom" JsonControlData="{&quot;id&quot;: &quot;cb3bfe97-a47f-47ca-bffb-bb9a5ff83d75&quot;, &quot;instanceId&quot;: &quot;92e416a5-6b09-46df-bc39-567082f29bd4&quot;, &quot;title&quot;: &quot;Conversations&quot;, &quot;description&quot;: &quot;Display Yammer group, user, topic or home feed&quot;, &quot;dataVersion&quot;: &quot;1.0&quot;, &quot;properties&quot;: {&quot;type&quot;:&quot;All&quot;,&quot;threadCount&quot;:4}, &quot;serverProcessedContent&quot;: {&quot;htmlStrings&quot;:{},&quot;searchablePlainTexts&quot;:{&quot;title&quot;:&quot;Conversations across Comms teams&quot;},&quot;imageSources&quot;:{},&quot;links&quot;:{}}, &quot;dynamicDataPaths&quot;: {}, &quot;dynamicDataValues&quot;: {}}" ControlId="cb3bfe97-a47f-47ca-bffb-bb9a5ff83d75" Order="1" Column="1" />
                <pnp:CanvasControl WebPartType="Custom" JsonControlData="{&quot;id&quot;: &quot;f6fdf4f8-4a24-437b-a127-32e66a5dd9b4&quot;, &quot;instanceId&quot;: &quot;52a682a7-7b56-422b-a8cc-2c03e5e78716&quot;, &quot;title&quot;: &quot;Twitter&quot;, &quot;description&quot;: &quot;Display a Twitter feed&quot;, &quot;dataVersion&quot;: &quot;1.0&quot;, &quot;properties&quot;: {&quot;displayAs&quot;:&quot;list&quot;,&quot;displayHeader&quot;:false,&quot;displayFooter&quot;:false,&quot;displayBorders&quot;:false,&quot;limit&quot;:&quot;3&quot;,&quot;term&quot;:&quot;@contosoinc&quot;,&quot;widthSlider&quot;:100,&quot;displayLightTheme&quot;:true}, &quot;serverProcessedContent&quot;: {&quot;htmlStrings&quot;:{},&quot;searchablePlainTexts&quot;:{&quot;title&quot;:&quot;Latest tweets&quot;},&quot;imageSources&quot;:{},&quot;links&quot;:{}}, &quot;dynamicDataPaths&quot;: {}, &quot;dynamicDataValues&quot;: {}}" ControlId="f6fdf4f8-4a24-437b-a127-32e66a5dd9b4" Order="1" Column="2" />
              </pnp:Controls>
            </pnp:Section>
          </pnp:Sections>
        </pnp:ClientSidePage>
        <pnp:ClientSidePage PageName="Singapore-trip-report.aspx" PromoteAsNewsArticle="true" PromoteAsTemplate="false" Overwrite="true" Title="Singapore trip report" ThumbnailUrl="">
          <pnp:Header Type="Custom" ServerRelativeImageUrl="{site}/SiteAssets/SitePages/Singapore-trip-report/39311-Singapore1920.1080.jpg" TranslateX="48.0916030534351" TranslateY="12.280701754386" LayoutType="FullWidthImage" TextAlignment="Center" ShowTopicHeader="true" ShowPublishDate="false" TopicHeader="September 2019" AlternativeText="" Authors="" AuthorByLine="" AuthorByLineId="-1" />
          <pnp:Sections>
            <pnp:Section Order="1" Type="OneColumn" BackgroundEmphasis="Neutral">
              <pnp:Controls>
                <pnp:CanvasControl WebPartType="People" JsonControlData="{&quot;id&quot;: &quot;7f718435-ee4d-431c-bdbf-9c4ff326f46e&quot;, &quot;instanceId&quot;: &quot;e478eb15-d821-474b-af89-8bf0c0e91743&quot;, &quot;title&quot;: &quot;People&quot;, &quot;description&quot;: &quot;Display selected people and their profiles&quot;, &quot;dataVersion&quot;: &quot;1.3&quot;, &quot;properties&quot;: {&quot;layout&quot;:1,&quot;persons&quot;:[{&quot;id&quot;:&quot;MiriamG@contoso.com&quot;,&quot;role&quot;:&quot;Chief Marketing Officer&quot;},{&quot;id&quot;:&quot;AdeleV@contoso.com&quot;,&quot;role&quot;:&quot;Retail Manager&quot;},{&quot;id&quot;:&quot;IsaiahL@contoso.com&quot;,&quot;role&quot;:&quot;Sales Rep&quot;},{&quot;id&quot;:&quot;MeganB@contoso.com&quot;,&quot;role&quot;:&quot;Marketing Manager&quot;},{&quot;id&quot;:&quot;DiegoS@contoso.com&quot;,&quot;role&quot;:&quot;HR Manager&quot;},{&quot;id&quot;:&quot;ChristieC@contoso.com&quot;,&quot;role&quot;:&quot;Buyer&quot;}]}, &quot;serverProcessedContent&quot;: {&quot;htmlStrings&quot;:{},&quot;searchablePlainTexts&quot;:{&quot;title&quot;:&quot;Contoso marketing team&quot;,&quot;persons[0].name&quot;:&quot;Miriam Graham&quot;,&quot;persons[1].name&quot;:&quot;Adele Vance&quot;,&quot;persons[2].name&quot;:&quot;Isaiah Langer&quot;,&quot;persons[3].name&quot;:&quot;Megan Bowen&quot;,&quot;persons[4].name&quot;:&quot;Diego Siciliani&quot;,&quot;persons[5].name&quot;:&quot;Christie Cline&quot;,&quot;persons[0].email&quot;:&quot;MiriamG@contoso.com&quot;,&quot;persons[1].email&quot;:&quot;AdeleV@contoso.com&quot;,&quot;persons[2].email&quot;:&quot;IsaiahL@contoso.com&quot;,&quot;persons[3].email&quot;:&quot;MeganB@contoso.com&quot;,&quot;persons[4].email&quot;:&quot;DiegoS@contoso.com&quot;,&quot;persons[5].email&quot;:&quot;ChristieC@contoso.com&quot;},&quot;imageSources&quot;:{},&quot;links&quot;:{}}, &quot;dynamicDataPaths&quot;: {}, &quot;dynamicDataValues&quot;: {}}" ControlId="7f718435-ee4d-431c-bdbf-9c4ff326f46e" Order="1" Column="1" />
              </pnp:Controls>
            </pnp:Section>
            <pnp:Section Order="2" Type="TwoColumnLeft">
              <pnp:Controls>
                <pnp:CanvasControl WebPartType="Text" ControlId="3d285d70-77a7-433b-9886-da52e94226d2" Order="1" Column="1">
                  <pnp:CanvasControlProperties>
                    <pnp:CanvasControlProperty Key="Text" Value="&lt;p&gt;&lt;span class=&quot;fontSizeXLarge&quot;&gt;In September, members of&amp;nbsp;the Contoso marketing team and myself took part in a 2-week visit with our partners in Singapore. The purpose of the trip was four-fold: to deeply engage with our Singapore sales leads; to conduct customer briefings; to get an inside look at our manufacturing process; and to get a tour of our new Singapore sales location set to open next year.&amp;nbsp;&amp;nbsp;&lt;/span&gt;&lt;/p&gt;&#xA;&#xA;&lt;p&gt;&lt;span class=&quot;fontSizeLarge&quot;&gt;&lt;em&gt;&lt;strong&gt;Note:&lt;/strong&gt;&lt;/em&gt;&amp;nbsp;This report covers highlights from 10 very deep and busy days. If there is information you'd like to see that is not covered here, you want more details, or if you have questions for me or the team members who attended, let us know.&lt;/span&gt;&lt;/p&gt;&#xA;" />
                  </pnp:CanvasControlProperties>
                </pnp:CanvasControl>
                <pnp:CanvasControl WebPartType="Text" ControlId="afabfdd6-f765-41db-969a-1250734a89ae" Order="1" Column="2">
                  <pnp:CanvasControlProperties>
                    <pnp:CanvasControlProperty Key="Text" Value="&lt;p&gt;While in Singapore we were able to conduct&amp;nbsp;15 customer briefings over a span of 3 days:&lt;/p&gt;&#xA;&#xA;&lt;div class=&quot;canvasRteResponsiveTable&quot;&gt;&#xA;&lt;div class=&quot;tableWrapper&quot;&gt;&#xA;&lt;table class=&quot;filledHeaderTableStyleNeutral&quot; title=&quot;Table&quot;&gt;&#xA;	&lt;tbody&gt;&#xA;		&lt;tr&gt;&#xA;			&lt;td&gt;&amp;nbsp;&lt;/td&gt;&#xA;			&lt;td&gt;SCHEDULED&lt;/td&gt;&#xA;			&lt;td style=&quot;width:56px;&quot;&gt;ACTUAL&lt;/td&gt;&#xA;			&lt;td style=&quot;width:86px;&quot;&gt;RESPONSES&lt;/td&gt;&#xA;		&lt;/tr&gt;&#xA;		&lt;tr&gt;&#xA;			&lt;td&gt;&lt;strong&gt;DAY 1&lt;/strong&gt;&lt;/td&gt;&#xA;			&lt;td&gt;6&lt;/td&gt;&#xA;			&lt;td style=&quot;width:56px;&quot;&gt;5&lt;/td&gt;&#xA;			&lt;td style=&quot;width:86px;&quot;&gt;8&lt;/td&gt;&#xA;		&lt;/tr&gt;&#xA;		&lt;tr&gt;&#xA;			&lt;td&gt;&lt;strong&gt;DAY 2&lt;/strong&gt;&lt;/td&gt;&#xA;			&lt;td&gt;6&lt;/td&gt;&#xA;			&lt;td style=&quot;width:56px;&quot;&gt;6&lt;/td&gt;&#xA;			&lt;td style=&quot;width:86px;&quot;&gt;12&lt;/td&gt;&#xA;		&lt;/tr&gt;&#xA;		&lt;tr&gt;&#xA;			&lt;td&gt;&lt;strong&gt;DAY 3&lt;/strong&gt;&lt;/td&gt;&#xA;			&lt;td&gt;5&lt;/td&gt;&#xA;			&lt;td style=&quot;width:56px;&quot;&gt;4&lt;/td&gt;&#xA;			&lt;td style=&quot;width:86px;&quot;&gt;7&lt;/td&gt;&#xA;		&lt;/tr&gt;&#xA;		&lt;tr&gt;&#xA;			&lt;td&gt;&lt;strong&gt;TOTAL&lt;/strong&gt;&lt;/td&gt;&#xA;			&lt;td&gt;17&lt;/td&gt;&#xA;			&lt;td style=&quot;width:56px;&quot;&gt;15&lt;/td&gt;&#xA;			&lt;td style=&quot;width:86px;&quot;&gt;27&lt;/td&gt;&#xA;		&lt;/tr&gt;&#xA;	&lt;/tbody&gt;&#xA;&lt;/table&gt;&#xA;&lt;/div&gt;&#xA;&lt;/div&gt;&#xA;" />
                  </pnp:CanvasControlProperties>
                </pnp:CanvasControl>
              </pnp:Controls>
            </pnp:Section>
            <pnp:Section Order="3" Type="OneColumn">
              <pnp:Controls>
                <pnp:CanvasControl WebPartType="ImageGallery" JsonControlData="{&quot;id&quot;: &quot;af8be689-990e-492a-81f7-ba3e4cd3ed9c&quot;, &quot;instanceId&quot;: &quot;1001dad4-8ed6-430f-a7e7-9656ec405e41&quot;, &quot;title&quot;: &quot;Image gallery&quot;, &quot;description&quot;: &quot;Spotlight your favorite images in a gallery&quot;, &quot;dataVersion&quot;: &quot;1.7&quot;, &quot;properties&quot;: {&quot;layout&quot;:2,&quot;carouselSettings&quot;:{&quot;autoplay&quot;:false,&quot;autoplaySpeed&quot;:5,&quot;dots&quot;:false,&quot;lazyLoad&quot;:true,&quot;metadata&quot;:true,&quot;swipe&quot;:true},&quot;gridSettings&quot;:{&quot;imageSize&quot;:3,&quot;imageCropping&quot;:1,&quot;imageAspectRatio&quot;:2,&quot;lightbox&quot;:false},&quot;imageSourceType&quot;:1,&quot;isRecursive&quot;:false,&quot;isCdnEnabledForList&quot;:false,&quot;hasDynamicModeEnabled&quot;:false,&quot;maxImagesCount&quot;:10,&quot;images&quot;:[{&quot;siteId&quot;:&quot;{sitecollectionid}&quot;,&quot;webId&quot;:&quot;{siteid}&quot;,&quot;listId&quot;:&quot;{listid:Site Assets}&quot;,&quot;id&quot;:&quot;{fileuniqueid:SiteAssets/SitePages/Singapore-trip-report/2200814861-Singapore1920.1080.jpg}&quot;,&quot;isInList&quot;:true,&quot;title&quot;:null,&quot;imageTileWidth&quot;:300},{&quot;siteId&quot;:&quot;{sitecollectionid}&quot;,&quot;webId&quot;:&quot;{siteid}&quot;,&quot;listId&quot;:&quot;{listid:Site Assets}&quot;,&quot;id&quot;:&quot;{fileuniqueid:SiteAssets/SitePages/Singapore-trip-report/9418337674singapore-airport.jpg}&quot;,&quot;isInList&quot;:true,&quot;title&quot;:null,&quot;imageTileWidth&quot;:300},{&quot;siteId&quot;:&quot;{sitecollectionid}&quot;,&quot;webId&quot;:&quot;{siteid}&quot;,&quot;listId&quot;:&quot;{listid:Site Assets}&quot;,&quot;id&quot;:&quot;{fileuniqueid:SiteAssets/SitePages/Singapore-trip-report/7851051212sergio-sala-1433115-unsplash.jpg}&quot;,&quot;isInList&quot;:true,&quot;title&quot;:null,&quot;imageTileWidth&quot;:300},{&quot;siteId&quot;:&quot;{sitecollectionid}&quot;,&quot;webId&quot;:&quot;{siteid}&quot;,&quot;listId&quot;:&quot;{listid:Site Assets}&quot;,&quot;id&quot;:&quot;{fileuniqueid:SiteAssets/SitePages/Singapore-trip-report/5404572832victor-garcia-741316-unsplash.jpg}&quot;,&quot;isInList&quot;:true,&quot;title&quot;:null,&quot;imageTileWidth&quot;:300},{&quot;siteId&quot;:&quot;{sitecollectionid}&quot;,&quot;webId&quot;:&quot;{siteid}&quot;,&quot;listId&quot;:&quot;{listid:Site Assets}&quot;,&quot;id&quot;:&quot;{fileuniqueid:SiteAssets/SitePages/Singapore-trip-report/2938599925hu-chen-656089-unsplash.jpg}&quot;,&quot;isInList&quot;:true,&quot;title&quot;:null,&quot;imageTileWidth&quot;:300},{&quot;siteId&quot;:&quot;{sitecollectionid}&quot;,&quot;webId&quot;:&quot;{siteid}&quot;,&quot;listId&quot;:&quot;{listid:Site Assets}&quot;,&quot;id&quot;:&quot;{fileuniqueid:SiteAssets/SitePages/Singapore-trip-report/5735711170-henry-co-180108-unsplash.jpg}&quot;,&quot;isInList&quot;:true,&quot;title&quot;:null,&quot;imageTileWidth&quot;:300},{&quot;siteId&quot;:&quot;{sitecollectionid}&quot;,&quot;webId&quot;:&quot;{siteid}&quot;,&quot;listId&quot;:&quot;{listid:Site Assets}&quot;,&quot;id&quot;:&quot;{fileuniqueid:SiteAssets/SitePages/Singapore-trip-report/80811432091200px-Singapore_skyline_at_sunset_viewed_from_Gardens_by_the_Bay_East_-_20120426.jpg}&quot;,&quot;isInList&quot;:true,&quot;title&quot;:null,&quot;imageTileWidth&quot;:300},{&quot;siteId&quot;:&quot;{sitecollectionid}&quot;,&quot;webId&quot;:&quot;{siteid}&quot;,&quot;listId&quot;:&quot;{listid:Site Assets}&quot;,&quot;id&quot;:&quot;{fileuniqueid:SiteAssets/SitePages/Singapore-trip-report/6881280523building-construction.jpg}&quot;,&quot;isInList&quot;:true,&quot;title&quot;:null,&quot;imageTileWidth&quot;:300}]}, &quot;serverProcessedContent&quot;: {&quot;htmlStrings&quot;:{},&quot;searchablePlainTexts&quot;:{&quot;images[0].description&quot;:&quot;&quot;,&quot;images[1].description&quot;:&quot;&quot;,&quot;images[2].description&quot;:&quot;&quot;,&quot;images[3].description&quot;:&quot;&quot;,&quot;images[4].description&quot;:&quot;&quot;,&quot;images[5].description&quot;:&quot;&quot;,&quot;images[6].description&quot;:&quot;&quot;,&quot;images[7].description&quot;:&quot;&quot;,&quot;images[0].altText&quot;:&quot;&quot;,&quot;images[1].altText&quot;:&quot;&quot;,&quot;images[2].altText&quot;:&quot;&quot;,&quot;images[3].altText&quot;:&quot;&quot;,&quot;images[4].altText&quot;:&quot;&quot;,&quot;images[5].altText&quot;:&quot;&quot;,&quot;images[6].altText&quot;:&quot;&quot;,&quot;images[7].altText&quot;:&quot;&quot;},&quot;imageSources&quot;:{&quot;images[0].url&quot;:&quot;{site}/SiteAssets/SitePages/Singapore-trip-report/2200814861-Singapore1920.1080.jpg&quot;,&quot;images[1].url&quot;:&quot;{site}/SiteAssets/SitePages/Singapore-trip-report/9418337674singapore-airport.jpg&quot;,&quot;images[2].url&quot;:&quot;{site}/SiteAssets/SitePages/Singapore-trip-report/7851051212sergio-sala-1433115-unsplash.jpg&quot;,&quot;images[3].url&quot;:&quot;{site}/SiteAssets/SitePages/Singapore-trip-report/5404572832victor-garcia-741316-unsplash.jpg&quot;,&quot;images[4].url&quot;:&quot;{site}/SiteAssets/SitePages/Singapore-trip-report/2938599925hu-chen-656089-unsplash.jpg&quot;,&quot;images[5].url&quot;:&quot;{site}/SiteAssets/SitePages/Singapore-trip-report/5735711170-henry-co-180108-unsplash.jpg&quot;,&quot;images[6].url&quot;:&quot;{site}/SiteAssets/SitePages/Singapore-trip-report/80811432091200px-Singapore_skyline_at_sunset_viewed_from_Gardens_by_the_Bay_East_-_20120426.jpg&quot;,&quot;images[7].url&quot;:&quot;{site}/SiteAssets/SitePages/Singapore-trip-report/6881280523building-construction.jpg&quot;},&quot;links&quot;:{},&quot;customMetadata&quot;:{&quot;images[0].url&quot;:{&quot;siteId&quot;:&quot;{sitecollectionid}&quot;,&quot;webId&quot;:&quot;{siteid}&quot;,&quot;listId&quot;:&quot;{listid:Site Assets}&quot;,&quot;uniqueId&quot;:&quot;{fileuniqueid:SiteAssets/SitePages/Singapore-trip-report/2200814861-Singapore1920.1080.jpg}&quot;,&quot;fixedWidth&quot;:300},&quot;images[1].url&quot;:{&quot;siteId&quot;:&quot;{sitecollectionid}&quot;,&quot;webId&quot;:&quot;{siteid}&quot;,&quot;listId&quot;:&quot;{listid:Site Assets}&quot;,&quot;uniqueId&quot;:&quot;{fileuniqueid:SiteAssets/SitePages/Singapore-trip-report/9418337674singapore-airport.jpg}&quot;,&quot;fixedWidth&quot;:300},&quot;images[2].url&quot;:{&quot;siteId&quot;:&quot;{sitecollectionid}&quot;,&quot;webId&quot;:&quot;{siteid}&quot;,&quot;listId&quot;:&quot;{listid:Site Assets}&quot;,&quot;uniqueId&quot;:&quot;{fileuniqueid:SiteAssets/SitePages/Singapore-trip-report/7851051212sergio-sala-1433115-unsplash.jpg}&quot;,&quot;fixedWidth&quot;:300},&quot;images[3].url&quot;:{&quot;siteId&quot;:&quot;{sitecollectionid}&quot;,&quot;webId&quot;:&quot;{siteid}&quot;,&quot;listId&quot;:&quot;{listid:Site Assets}&quot;,&quot;uniqueId&quot;:&quot;{fileuniqueid:SiteAssets/SitePages/Singapore-trip-report/5404572832victor-garcia-741316-unsplash.jpg}&quot;,&quot;fixedWidth&quot;:300},&quot;images[4].url&quot;:{&quot;siteId&quot;:&quot;{sitecollectionid}&quot;,&quot;webId&quot;:&quot;{siteid}&quot;,&quot;listId&quot;:&quot;{listid:Site Assets}&quot;,&quot;uniqueId&quot;:&quot;{fileuniqueid:SiteAssets/SitePages/Singapore-trip-report/2938599925hu-chen-656089-unsplash.jpg}&quot;,&quot;fixedWidth&quot;:300},&quot;images[5].url&quot;:{&quot;siteId&quot;:&quot;{sitecollectionid}&quot;,&quot;webId&quot;:&quot;{siteid}&quot;,&quot;listId&quot;:&quot;{listid:Site Assets}&quot;,&quot;uniqueId&quot;:&quot;{fileuniqueid:SiteAssets/SitePages/Singapore-trip-report/5735711170-henry-co-180108-unsplash.jpg}&quot;,&quot;fixedWidth&quot;:300},&quot;images[6].url&quot;:{&quot;siteId&quot;:&quot;{sitecollectionid}&quot;,&quot;webId&quot;:&quot;{siteid}&quot;,&quot;listId&quot;:&quot;{listid:Site Assets}&quot;,&quot;uniqueId&quot;:&quot;{fileuniqueid:SiteAssets/SitePages/Singapore-trip-report/80811432091200px-Singapore_skyline_at_sunset_viewed_from_Gardens_by_the_Bay_East_-_20120426.jpg}&quot;,&quot;fixedWidth&quot;:300},&quot;images[7].url&quot;:{&quot;siteId&quot;:&quot;{sitecollectionid}&quot;,&quot;webId&quot;:&quot;{siteid}&quot;,&quot;listId&quot;:&quot;{listid:Site Assets}&quot;,&quot;uniqueId&quot;:&quot;{fileuniqueid:SiteAssets/SitePages/Singapore-trip-report/6881280523building-construction.jpg}&quot;,&quot;fixedWidth&quot;:300}},&quot;componentDependencies&quot;:{&quot;layoutComponentId&quot;:&quot;44777806-007b-4c18-9263-f1e16a726911&quot;}}, &quot;dynamicDataPaths&quot;: {}, &quot;dynamicDataValues&quot;: {}}" ControlId="af8be689-990e-492a-81f7-ba3e4cd3ed9c" Order="1" Column="1" />
              </pnp:Controls>
            </pnp:Section>
            <pnp:Section Order="4" Type="TwoColumn">
              <pnp:Controls>
                <pnp:CanvasControl WebPartType="Text" ControlId="1eea9461-fbd5-432a-9187-bf601562805f" Order="1" Column="1">
                  <pnp:CanvasControlProperties>
                    <pnp:CanvasControlProperty Key="Text" Value="&lt;h3&gt;&lt;span class=&quot;fontColorThemePrimary&quot;&gt;Highlights of our visit&lt;/span&gt;&lt;/h3&gt;&#xA;&#xA;&lt;ul&gt;&#xA;	&lt;li&gt;&#xA;	&lt;p&gt;Face-to-face briefings with 15 key customers.&lt;/p&gt;&#xA;	&lt;/li&gt;&#xA;	&lt;li&gt;&#xA;	&lt;p&gt;A planning and strategy meeting with Contoso Singapore sales leads Michael Zhou, Dylan Price, and Bo Xiong.&amp;nbsp;We established new channels to streamline efficiency between our U.S. and Singapore partners.&amp;nbsp;&lt;/p&gt;&#xA;	&lt;/li&gt;&#xA;	&lt;li&gt;&#xA;	&lt;p&gt;A meeting with&amp;nbsp;manufacturing partners at Fabrikam, Inc. for a tour of their facility and an overview of their manufacturing&amp;nbsp;process.&amp;nbsp;&amp;nbsp;&lt;/p&gt;&#xA;	&lt;/li&gt;&#xA;	&lt;li&gt;A tour of the&amp;nbsp;new Contoso Singapore office to which our Sales department will be moving soon.&lt;/li&gt;&#xA;&lt;/ul&gt;&#xA;" />
                  </pnp:CanvasControlProperties>
                </pnp:CanvasControl>
                <pnp:CanvasControl WebPartType="Text" ControlId="2e9c4e0e-2cad-45ca-92e5-d7990d367e59" Order="1" Column="2">
                  <pnp:CanvasControlProperties>
                    <pnp:CanvasControlProperty Key="Text" Value="&lt;h3&gt;&lt;span class=&quot;fontColorThemePrimary&quot;&gt;Key outcomes and takeaways&amp;nbsp;&lt;/span&gt;&lt;/h3&gt;&#xA;&#xA;&lt;ul&gt;&#xA;	&lt;li&gt;&#xA;	&lt;p&gt;Feedback from customer briefings indicate a high level of satisfaction, but we have more work to do to continue increasing adoption rate.&lt;/p&gt;&#xA;	&lt;/li&gt;&#xA;	&lt;li&gt;&#xA;	&lt;p&gt;Face-to-face meetings helped establish a meaningful rapport with sales partners in Singapore.&amp;nbsp;&lt;/p&gt;&#xA;	&lt;/li&gt;&#xA;	&lt;li&gt;&#xA;	&lt;p&gt;Established new channels of communication to streamline efficiency and teamwork, including the use of Teams for work on key initiatives.&amp;nbsp;&lt;/p&gt;&#xA;	&lt;/li&gt;&#xA;	&lt;li&gt;&#xA;	&lt;p&gt;Documented our manufacturing process, including images and visuals, which are presented later in this document.&amp;nbsp;&lt;/p&gt;&#xA;	&lt;/li&gt;&#xA;&lt;/ul&gt;&#xA;" />
                  </pnp:CanvasControlProperties>
                </pnp:CanvasControl>
              </pnp:Controls>
            </pnp:Section>
            <pnp:Section Order="5" Type="TwoColumn">
              <pnp:Controls>
                <pnp:CanvasControl WebPartType="Image" JsonControlData="{&quot;id&quot;: &quot;d1d91016-032f-456d-98a4-721247c305e8&quot;, &quot;instanceId&quot;: &quot;c6aa0f5d-6866-48c4-a971-a8db3758e5ab&quot;, &quot;title&quot;: &quot;Image&quot;, &quot;description&quot;: &quot;Show an image on your page&quot;, &quot;dataVersion&quot;: &quot;1.8&quot;, &quot;properties&quot;: {&quot;imageSourceType&quot;:2,&quot;altText&quot;:&quot;&quot;,&quot;overlayText&quot;:&quot;&quot;,&quot;fileName&quot;:&quot;&quot;,&quot;siteId&quot;:&quot;{sitecollectionid}&quot;,&quot;webId&quot;:&quot;{siteid}&quot;,&quot;listId&quot;:&quot;{{listid:Site Assets}}&quot;,&quot;uniqueId&quot;:&quot;{fileuniqueid:SiteAssets/SitePages/Singapore-trip-report/5735711170-henry-co-180108-unsplash.jpg}&quot;,&quot;imgWidth&quot;:4896,&quot;imgHeight&quot;:3264,&quot;resizeCoefficient&quot;:1,&quot;alignment&quot;:&quot;Center&quot;,&quot;fixAspectRatio&quot;:false}, &quot;serverProcessedContent&quot;: {&quot;htmlStrings&quot;:{},&quot;searchablePlainTexts&quot;:{&quot;captionText&quot;:&quot;&quot;},&quot;imageSources&quot;:{&quot;imageSource&quot;:&quot;{site}/SiteAssets/SitePages/Singapore-trip-report/5735711170-henry-co-180108-unsplash.jpg&quot;},&quot;links&quot;:{&quot;linkUrl&quot;:&quot;&quot;},&quot;customMetadata&quot;:{&quot;imageSource&quot;:{&quot;siteId&quot;:&quot;{sitecollectionid}&quot;,&quot;webId&quot;:&quot;{siteid}&quot;,&quot;listId&quot;:&quot;{{listid:Site Assets}}&quot;,&quot;uniqueId&quot;:&quot;{fileuniqueid:SiteAssets/SitePages/Singapore-trip-report/5735711170-henry-co-180108-unsplash.jpg}&quot;,&quot;width&quot;:4896,&quot;height&quot;:3264}}}, &quot;dynamicDataPaths&quot;: {}, &quot;dynamicDataValues&quot;: {}}" ControlId="d1d91016-032f-456d-98a4-721247c305e8" Order="1" Column="1" />
                <pnp:CanvasControl WebPartType="Text" ControlId="077cad66-d8ef-411d-aa8b-6f1740b4ec7d" Order="1" Column="2">
                  <pnp:CanvasControlProperties>
                    <pnp:CanvasControlProperty Key="Text" Value="&lt;h3&gt;&lt;span class=&quot;fontColorThemePrimary&quot;&gt;Contoso Singapore building tour&lt;/span&gt;&lt;/h3&gt;&#xA;&#xA;&lt;p&gt;Thanks to our facilities partners for a&amp;nbsp;tour of the new building where our Contoso sales department will be housed. Construction is nearly finished, and I am pleased to&amp;nbsp;&lt;a data-interception=&quot;on&quot; href=&quot;https://contosoelectronics1a.sharepoint.com/sites/LeadershipConnection/SitePages/Singapore-building-update---May-2019.aspx&quot;&gt;hear that we are on&amp;nbsp;track for the target opening&lt;/a&gt;.&amp;nbsp;&amp;nbsp;&lt;/p&gt;&#xA;&#xA;&lt;p&gt;Singapore itself has emerged as a global powerhouse over the past decades, with the presence of major international companies growing every day.&amp;nbsp;Singapore&amp;nbsp;matches our own innovative spirit, integrity, and passion for growth.&amp;nbsp;We cannot be more excited for the upcoming opening.&lt;/p&gt;&#xA;&#xA;&lt;p&gt;&lt;strong&gt;–&lt;/strong&gt;&lt;/p&gt;&#xA;&#xA;&lt;p&gt;&lt;span class=&quot;fontSizeXLarge&quot;&gt;&lt;em&gt;“It is an amazing space that will serve as a hub for our global community, and we are excited for the potential it brings.”&lt;/em&gt;&lt;/span&gt;&lt;/p&gt;&#xA;&#xA;&lt;p&gt;&lt;span class=&quot;fontColorThemeDark&quot;&gt;&lt;span class=&quot;fontSizeMediumPlus&quot;&gt;&lt;strong&gt;MIRIAM GRAHAM&lt;/strong&gt;&lt;/span&gt;&lt;/span&gt;&lt;/p&gt;&#xA;" />
                  </pnp:CanvasControlProperties>
                </pnp:CanvasControl>
              </pnp:Controls>
            </pnp:Section>
            <pnp:Section Order="6" Type="TwoColumn" BackgroundEmphasis="Neutral">
              <pnp:Controls>
                <pnp:CanvasControl WebPartType="Text" ControlId="8f0ca4ba-cf79-4637-befc-8affcaaa1d15" Order="1" Column="1">
                  <pnp:CanvasControlProperties>
                    <pnp:CanvasControlProperty Key="Text" Value="&lt;h3&gt;&lt;span class=&quot;fontColorThemePrimary&quot;&gt;Customer briefing&amp;nbsp;feedback&amp;nbsp;&lt;/span&gt;&lt;/h3&gt;&#xA;&#xA;&lt;p&gt;Each Contoso Electronics&amp;nbsp;briefing attendee was asked to provide feedback about the meetings they participated in. We had 3 primary goals: to find out if the sales team&amp;nbsp;was getting value from these meetings, if the customer was perceived to be getting value, and if we could identify customers that could potentially make good reference accounts for case studies and other customer evidence.&lt;/p&gt;&#xA;&#xA;&lt;p&gt;&amp;nbsp;&lt;/p&gt;&#xA;&#xA;&lt;p&gt;average scores below reflect only the meetings that took place rather than all scores including the few that didn’t show for their meeting.&lt;/p&gt;&#xA;&#xA;&lt;p&gt;&lt;strong&gt;Q:&lt;/strong&gt;&amp;nbsp;Was the customer meeting a good use of your time:&amp;nbsp;&lt;strong&gt;8.27&amp;nbsp;rating&lt;br&gt;&#xA;Q:&lt;/strong&gt;&amp;nbsp;Do you feel the customer got value from the meeting:&amp;nbsp;&lt;strong&gt;8.40&amp;nbsp;rating&lt;/strong&gt;&lt;/p&gt;&#xA;" />
                  </pnp:CanvasControlProperties>
                </pnp:CanvasControl>
                <pnp:CanvasControl WebPartType="DocumentEmbed" JsonControlData="{&quot;id&quot;: &quot;b7dd04e1-19ce-4b24-9132-b60a1c2b910d&quot;, &quot;instanceId&quot;: &quot;fa3c786a-39f0-4af5-81d9-cffb4d565eff&quot;, &quot;title&quot;: &quot;File viewer&quot;, &quot;description&quot;: &quot;Display a document or other file on your page. You can show a file from most applications including Word, Excel, PowerPoint, Visio, PDF, 3D, and others&quot;, &quot;dataVersion&quot;: &quot;1.4&quot;, &quot;properties&quot;: {&quot;authorName&quot;:&quot;Katie Swanson&quot;,&quot;chartitem&quot;:&quot;&quot;,&quot;endrange&quot;:&quot;&quot;,&quot;excelSettingsType&quot;:&quot;&quot;,&quot;file&quot;:&quot;{hosturl}{site}/Shared%20Documents/Singapore_CustomerBriefings_97616.pptx&quot;,&quot;listId&quot;:&quot;{listid:Documents}&quot;,&quot;modifiedAt&quot;:&quot;2019-09-17T03:24:20Z&quot;,&quot;photoUrl&quot;:&quot;/_layouts/15/userphoto.aspx?size=S&amp;accountname=Katie%40contoso.com&quot;,&quot;rangeitem&quot;:&quot;&quot;,&quot;siteId&quot;:&quot;{sitecollectionid}&quot;,&quot;startPage&quot;:1,&quot;startrange&quot;:&quot;&quot;,&quot;tableitem&quot;:&quot;&quot;,&quot;uniqueId&quot;:&quot;{fileuniqueid:Shared Documents/Singapore_CustomerBriefings_97616.pptx}&quot;,&quot;wdallowinteractivity&quot;:true,&quot;wdhidegridlines&quot;:true,&quot;wdhideheaders&quot;:true,&quot;webId&quot;:&quot;{siteid}&quot;,&quot;webAbsoluteUrl&quot;:&quot;{hosturl}{site}&quot;}, &quot;serverProcessedContent&quot;: {&quot;htmlStrings&quot;:{},&quot;searchablePlainTexts&quot;:{&quot;annotation&quot;:&quot;Key themes and insights we learned from talking to customers\n&quot;,&quot;title&quot;:&quot;Singapore_CustomerBriefings_97616&quot;},&quot;imageSources&quot;:{},&quot;links&quot;:{&quot;serverRelativeUrl&quot;:&quot;{site}/Shared%20Documents/Singapore_CustomerBriefings_97616.pptx&quot;,&quot;wopiurl&quot;:&quot;{hosturl}{site}/_layouts/15/Doc.aspx?sourcedoc=%7B{fileuniqueid:Shared Documents/Singapore_CustomerBriefings_97616.pptx}%7D&amp;file=Singapore_CustomerBriefings_97616.pptx&amp;action=embedview&amp;mobileredirect=true&quot;}}, &quot;dynamicDataPaths&quot;: {}, &quot;dynamicDataValues&quot;: {}}" ControlId="b7dd04e1-19ce-4b24-9132-b60a1c2b910d" Order="1" Column="2" />
              </pnp:Controls>
            </pnp:Section>
          </pnp:Sections>
        </pnp:ClientSidePage>
        <pnp:ClientSidePage PageName="How-apps-can-make-corporate-communications-easier.aspx" PromoteAsNewsArticle="true" PromoteAsTemplate="false" Overwrite="true" Title="How apps can make corporate communications easier" ThumbnailUrl="{hosturl}{site}/_layouts/15/getpreview.ashx?guidSite={sitecollectionid}&amp;guidWeb={siteid}&amp;guidFile={fileuniqueid:SiteAssets/SitePages/How-apps-can-make-corporate-communications-easier/rawpixel-597438-unsplash.jpg}&amp;ext=jpg">
          <pnp:Header Type="Default" LayoutType="NoImage" TextAlignment="Center" ShowTopicHeader="true" ShowPublishDate="false" TopicHeader="communications" AlternativeText="" Authors="" AuthorByLine="" AuthorByLineId="-1" />
          <pnp:Sections>
            <pnp:Section Order="1" Type="OneColumn">
              <pnp:Controls>
                <pnp:CanvasControl WebPartType="Text" ControlId="f653f26e-8f6a-4618-9b6f-9f0c2b388f0b" Order="1" Column="1">
                  <pnp:CanvasControlProperties>
                    <pnp:CanvasControlProperty Key="Text" Value="Without being able to communicate goals and expectations, a business can’t grow. Although corporate communication is generally associated more with large corporations, with their dizzying number of departments and sub-departments, this statement is equally applicable to smaller enterprises, where employees might need to take on multiple roles." />
                  </pnp:CanvasControlProperties>
                </pnp:CanvasControl>
              </pnp:Controls>
            </pnp:Section>
          </pnp:Sections>
        </pnp:ClientSidePage>
        <pnp:ClientSidePage PageName="Welcome-to--CommsChat.aspx" PromoteAsNewsArticle="true" PromoteAsTemplate="false" Overwrite="true" Title="Welcome to #CommsChat" ThumbnailUrl="{hosturl}{site}/_layouts/15/getpreview.ashx?guidSite={sitecollectionid}&amp;guidWeb={siteid}&amp;guidFile={fileuniqueid:SiteAssets/SitePages/Welcome-to--CommsChat/studio-microphone-in-front-of-radio-station-PBWVM4G.jpg}&amp;ext=jpg">
          <pnp:Header Type="Default" LayoutType="NoImage" TextAlignment="Center" ShowTopicHeader="true" ShowPublishDate="false" TopicHeader="communications" AlternativeText="" Authors="" AuthorByLine="" AuthorByLineId="-1" />
          <pnp:Sections>
            <pnp:Section Order="1" Type="OneColumn">
              <pnp:Controls>
                <pnp:CanvasControl WebPartType="Text" ControlId="226c7ed3-fd96-419b-b92b-67b4c5f0f53e" Order="1" Column="1">
                  <pnp:CanvasControlProperties>
                    <pnp:CanvasControlProperty Key="Text" Value="Contoso's Miriam Graham and Lee Gu&amp;nbsp;go behind the scenes talking with internal and external experts to reveal how Contoso can work best for you." />
                  </pnp:CanvasControlProperties>
                </pnp:CanvasControl>
              </pnp:Controls>
            </pnp:Section>
          </pnp:Sections>
        </pnp:ClientSidePage>
        <pnp:ClientSidePage PageName="Strategic-communication--How-to-develop-strategic-massaging-and-positioning.aspx" PromoteAsNewsArticle="true" PromoteAsTemplate="false" Overwrite="true" Title="Strategic communication: How to develop strategic massaging and positioning" ThumbnailUrl="{hosturl}{site}/_layouts/15/getpreview.ashx?guidSite={sitecollectionid}&amp;guidWeb={siteid}&amp;guidFile={fileuniqueid:SiteAssets/SitePages/Strategic-communication--How-to-develop-strategic-massaging-and-positioning/business-people-planning-strategy-in-office-GRVBWNJ.jpg}&amp;ext=jpg">
          <pnp:Header Type="Default" LayoutType="NoImage" TextAlignment="Center" ShowTopicHeader="true" ShowPublishDate="false" TopicHeader="communication" AlternativeText="" Authors="" AuthorByLine="" AuthorByLineId="-1" />
          <pnp:Sections>
            <pnp:Section Order="1" Type="OneColumn">
              <pnp:Controls>
                <pnp:CanvasControl WebPartType="Text" ControlId="8085cdbb-56aa-45ee-b90c-20f6e5c9b65f" Order="1" Column="1">
                  <pnp:CanvasControlProperties>
                    <pnp:CanvasControlProperty Key="Text" Value="This article covers the essentials of strategic communication. The goal is to explain why it is critical that companies understand strategic messaging and positioning. In addition, we will discuss some practical and actionable approaches to help you design strategic messaging and product positioning." />
                  </pnp:CanvasControlProperties>
                </pnp:CanvasControl>
              </pnp:Controls>
            </pnp:Section>
          </pnp:Sections>
        </pnp:ClientSidePage>
      </pnp:ClientSidePages>
      <pnp:Header Layout="Compact" BackgroundEmphasis="Strong" />
    </pnp:ProvisioningTemplate>
  </pnp:Templates>
</pnp:Provisioning>